{"event_id":"842b19e0-bf90-4d20-9c6a-432d0992c3e9","time":null,"contest_time":"","state":{"finalized":"","started":"","thawed":"","frozen":"","ended":"","end_of_updates":""},"rows":[{"rank":1,"team_id":5,"score":{"total_time":49,"num_solved":4},"problems":[{"solved":false,"num_judged":0,"problem_id":"Box","num_pending":0},{"solved":true,"num_judged":1,"time":12,"problem_id":"Colour","num_pending":0},{"solved":true,"num_judged":1,"time":12,"problem_id":"Game","num_pending":0},{"solved":false,"num_judged":0,"problem_id":"Hello","num_pending":0},{"solved":false,"num_judged":0,"problem_id":"Magic","num_pending":0},{"solved":true,"num_judged":1,"time":12,"problem_id":"Matrix","num_pending":0},{"solved":false,"num_judged":0,"problem_id":"Rooms","num_pending":0},{"solved":true,"num_judged":1,"time":13,"problem_id":"SumIt","num_pending":0},{"solved":false,"num_judged":0,"problem_id":"Tax","num_pending":0}],"teamName":null},{"rank":2,"team_id":1,"score":{"total_time":22,"num_solved":3},"problems":[{"solved":false,"num_judged":0,"problem_id":"Box","num_pending":0},{"solved":true,"num_judged":1,"time":8,"problem_id":"Colour","num_pending":0},{"solved":false,"num_judged":0,"problem_id":"Game","num_pending":0},{"solved":false,"num_judged":0,"problem_id":"Hello","num_pending":0},{"solved":false,"num_judged":0,"problem_id":"Magic","num_pending":0},{"solved":true,"num_judged":1,"time":8,"problem_id":"Matrix","num_pending":0},{"solved":true,"num_judged":1,"time":6,"problem_id":"Rooms","num_pending":0},{"solved":false,"num_judged":0,"problem_id":"SumIt","num_pending":0},{"solved":false,"num_judged":0,"problem_id":"Tax","num_pending":0}],"teamName":null},{"rank":3,"team_id":13,"score":{"total_time":86,"num_solved":3},"problems":[{"solved":false,"num_judged":0,"problem_id":"Box","num_pending":0},{"solved":true,"num_judged":1,"time":29,"problem_id":"Colour","num_pending":0},{"solved":true,"num_judged":1,"time":29,"problem_id":"Game","num_pending":0},{"solved":false,"num_judged":0,"problem_id":"Hello","num_pending":0},{"solved":true,"num_judged":1,"time":28,"problem_id":"Magic","num_pending":0},{"solved":false,"num_judged":0,"problem_id":"Matrix","num_pending":0},{"solved":false,"num_judged":0,"problem_id":"Rooms","num_pending":0},{"solved":false,"num_judged":0,"problem_id":"SumIt","num_pending":0},{"solved":false,"num_judged":0,"problem_id":"Tax","num_pending":0}],"teamName":null},{"rank":4,"team_id":2,"score":{"total_time":4,"num_solved":2},"problems":[{"solved":false,"num_judged":0,"problem_id":"Box","num_pending":0},{"solved":true,"num_judged":1,"time":2,"problem_id":"Colour","num_pending":0},{"solved":false,"num_judged":0,"problem_id":"Game","num_pending":0},{"solved":false,"num_judged":0,"problem_id":"Hello","num_pending":0},{"solved":true,"num_judged":1,"time":2,"problem_id":"Magic","num_pending":0},{"solved":false,"num_judged":0,"problem_id":"Matrix","num_pending":0},{"solved":false,"num_judged":0,"problem_id":"Rooms","num_pending":0},{"solved":false,"num_judged":0,"problem_id":"SumIt","num_pending":0},{"solved":false,"num_judged":0,"problem_id":"Tax","num_pending":0}],"teamName":null},{"rank":5,"team_id":10,"score":{"total_time":55,"num_solved":2},"problems":[{"solved":false,"num_judged":0,"problem_id":"Box","num_pending":0},{"solved":false,"num_judged":0,"problem_id":"Colour","num_pending":0},{"solved":false,"num_judged":0,"problem_id":"Game","num_pending":0},{"solved":true,"num_judged":1,"time":27,"problem_id":"Hello","num_pending":0},{"solved":false,"num_judged":0,"problem_id":"Magic","num_pending":0},{"solved":true,"num_judged":1,"time":28,"problem_id":"Matrix","num_pending":0},{"solved":false,"num_judged":0,"problem_id":"Rooms","num_pending":0},{"solved":false,"num_judged":0,"problem_id":"SumIt","num_pending":0},{"solved":false,"num_judged":0,"problem_id":"Tax","num_pending":0}],"teamName":null},{"rank":6,"team_id":4,"score":{"total_time":1,"num_solved":1},"problems":[{"solved":false,"num_judged":0,"problem_id":"Box","num_pending":0},{"solved":false,"num_judged":0,"problem_id":"Colour","num_pending":0},{"solved":false,"num_judged":0,"problem_id":"Game","num_pending":0},{"solved":false,"num_judged":0,"problem_id":"Hello","num_pending":0},{"solved":false,"num_judged":0,"problem_id":"Magic","num_pending":0},{"solved":true,"num_judged":1,"time":1,"problem_id":"Matrix","num_pending":0},{"solved":false,"num_judged":0,"problem_id":"Rooms","num_pending":0},{"solved":false,"num_judged":0,"problem_id":"SumIt","num_pending":0},{"solved":false,"num_judged":0,"problem_id":"Tax","num_pending":0}],"teamName":null},{"rank":7,"team_id":18,"score":{"total_time":3,"num_solved":1},"problems":[{"solved":false,"num_judged":0,"problem_id":"Box","num_pending":0},{"solved":false,"num_judged":0,"problem_id":"Colour","num_pending":0},{"solved":false,"num_judged":1,"problem_id":"Game","num_pending":0},{"solved":false,"num_judged":0,"problem_id":"Hello","num_pending":0},{"solved":false,"num_judged":0,"problem_id":"Magic","num_pending":0},{"solved":false,"num_judged":0,"problem_id":"Matrix","num_pending":0},{"solved":false,"num_judged":0,"problem_id":"Rooms","num_pending":0},{"solved":true,"num_judged":1,"time":3,"problem_id":"SumIt","num_pending":0},{"solved":false,"num_judged":0,"problem_id":"Tax","num_pending":0}],"teamName":null},{"rank":8,"team_id":9,"score":{"total_time":5,"num_solved":1},"problems":[{"solved":false,"num_judged":0,"problem_id":"Box","num_pending":0},{"solved":false,"num_judged":0,"problem_id":"Colour","num_pending":0},{"solved":false,"num_judged":0,"problem_id":"Game","num_pending":0},{"solved":true,"num_judged":1,"time":5,"problem_id":"Hello","num_pending":0},{"solved":false,"num_judged":0,"problem_id":"Magic","num_pending":0},{"solved":false,"num_judged":0,"problem_id":"Matrix","num_pending":0},{"solved":false,"num_judged":0,"problem_id":"Rooms","num_pending":0},{"solved":false,"num_judged":0,"problem_id":"SumIt","num_pending":0},{"solved":false,"num_judged":0,"problem_id":"Tax","num_pending":0}],"teamName":null},{"rank":9,"team_id":21,"score":{"total_time":16,"num_solved":1},"problems":[{"solved":false,"num_judged":0,"problem_id":"Box","num_pending":0},{"solved":false,"num_judged":0,"problem_id":"Colour","num_pending":0},{"solved":false,"num_judged":0,"problem_id":"Game","num_pending":0},{"solved":true,"num_judged":1,"time":16,"problem_id":"Hello","num_pending":0},{"solved":false,"num_judged":0,"problem_id":"Magic","num_pending":0},{"solved":false,"num_judged":0,"problem_id":"Matrix","num_pending":0},{"solved":false,"num_judged":0,"problem_id":"Rooms","num_pending":0},{"solved":false,"num_judged":0,"problem_id":"SumIt","num_pending":0},{"solved":false,"num_judged":0,"problem_id":"Tax","num_pending":0}],"teamName":null},{"rank":10,"team_id":3,"score":{"total_time":0,"num_solved":0},"problems":[{"solved":false,"num_judged":0,"problem_id":"Box","num_pending":0},{"solved":false,"num_judged":0,"problem_id":"Colour","num_pending":0},{"solved":false,"num_judged":0,"problem_id":"Game","num_pending":0},{"solved":false,"num_judged":0,"problem_id":"Hello","num_pending":0},{"solved":false,"num_judged":0,"problem_id":"Magic","num_pending":0},{"solved":false,"num_judged":0,"problem_id":"Matrix","num_pending":0},{"solved":false,"num_judged":0,"problem_id":"Rooms","num_pending":0},{"solved":false,"num_judged":0,"problem_id":"SumIt","num_pending":0},{"solved":false,"num_judged":0,"problem_id":"Tax","num_pending":0}],"teamName":null},{"rank":10,"team_id":6,"score":{"total_time":0,"num_solved":0},"problems":[{"solved":false,"num_judged":0,"problem_id":"Box","num_pending":0},{"solved":false,"num_judged":0,"problem_id":"Colour","num_pending":0},{"solved":false,"num_judged":0,"problem_id":"Game","num_pending":0},{"solved":false,"num_judged":0,"problem_id":"Hello","num_pending":0},{"solved":false,"num_judged":0,"problem_id":"Magic","num_pending":0},{"solved":false,"num_judged":0,"problem_id":"Matrix","num_pending":0},{"solved":false,"num_judged":0,"problem_id":"Rooms","num_pending":0},{"solved":false,"num_judged":0,"problem_id":"SumIt","num_pending":0},{"solved":false,"num_judged":0,"problem_id":"Tax","num_pending":0}],"teamName":null},{"rank":10,"team_id":8,"score":{"total_time":0,"num_solved":0},"problems":[{"solved":false,"num_judged":0,"problem_id":"Box","num_pending":0},{"solved":false,"num_judged":0,"problem_id":"Colour","num_pending":0},{"solved":false,"num_judged":0,"problem_id":"Game","num_pending":0},{"solved":false,"num_judged":0,"problem_id":"Hello","num_pending":0},{"solved":false,"num_judged":0,"problem_id":"Magic","num_pending":0},{"solved":false,"num_judged":0,"problem_id":"Matrix","num_pending":0},{"solved":false,"num_judged":0,"problem_id":"Rooms","num_pending":0},{"solved":false,"num_judged":0,"problem_id":"SumIt","num_pending":0},{"solved":false,"num_judged":0,"problem_id":"Tax","num_pending":0}],"teamName":null},{"rank":10,"team_id":12,"score":{"total_time":0,"num_solved":0},"problems":[{"solved":false,"num_judged":0,"problem_id":"Box","num_pending":0},{"solved":false,"num_judged":0,"problem_id":"Colour","num_pending":0},{"solved":false,"num_judged":0,"problem_id":"Game","num_pending":0},{"solved":false,"num_judged":0,"problem_id":"Hello","num_pending":0},{"solved":false,"num_judged":0,"problem_id":"Magic","num_pending":0},{"solved":false,"num_judged":0,"problem_id":"Matrix","num_pending":0},{"solved":false,"num_judged":0,"problem_id":"Rooms","num_pending":0},{"solved":false,"num_judged":0,"problem_id":"SumIt","num_pending":0},{"solved":false,"num_judged":0,"problem_id":"Tax","num_pending":0}],"teamName":null},{"rank":10,"team_id":11,"score":{"total_time":0,"num_solved":0},"problems":[{"solved":false,"num_judged":0,"problem_id":"Box","num_pending":0},{"solved":false,"num_judged":0,"problem_id":"Colour","num_pending":0},{"solved":false,"num_judged":0,"problem_id":"Game","num_pending":0},{"solved":false,"num_judged":0,"problem_id":"Hello","num_pending":0},{"solved":false,"num_judged":0,"problem_id":"Magic","num_pending":0},{"solved":false,"num_judged":0,"problem_id":"Matrix","num_pending":0},{"solved":false,"num_judged":0,"problem_id":"Rooms","num_pending":0},{"solved":false,"num_judged":0,"problem_id":"SumIt","num_pending":0},{"solved":false,"num_judged":0,"problem_id":"Tax","num_pending":0}],"teamName":null},{"rank":10,"team_id":14,"score":{"total_time":0,"num_solved":0},"problems":[{"solved":false,"num_judged":0,"problem_id":"Box","num_pending":0},{"solved":false,"num_judged":0,"problem_id":"Colour","num_pending":0},{"solved":false,"num_judged":0,"problem_id":"Game","num_pending":0},{"solved":false,"num_judged":0,"problem_id":"Hello","num_pending":0},{"solved":false,"num_judged":0,"problem_id":"Magic","num_pending":0},{"solved":false,"num_judged":0,"problem_id":"Matrix","num_pending":0},{"solved":false,"num_judged":0,"problem_id":"Rooms","num_pending":0},{"solved":false,"num_judged":0,"problem_id":"SumIt","num_pending":0},{"solved":false,"num_judged":0,"problem_id":"Tax","num_pending":0}],"teamName":null},{"rank":10,"team_id":15,"score":{"total_time":0,"num_solved":0},"problems":[{"solved":false,"num_judged":0,"problem_id":"Box","num_pending":0},{"solved":false,"num_judged":0,"problem_id":"Colour","num_pending":0},{"solved":false,"num_judged":0,"problem_id":"Game","num_pending":0},{"solved":false,"num_judged":0,"problem_id":"Hello","num_pending":0},{"solved":false,"num_judged":0,"problem_id":"Magic","num_pending":0},{"solved":false,"num_judged":0,"problem_id":"Matrix","num_pending":0},{"solved":false,"num_judged":0,"problem_id":"Rooms","num_pending":0},{"solved":false,"num_judged":0,"problem_id":"SumIt","num_pending":0},{"solved":false,"num_judged":0,"problem_id":"Tax","num_pending":0}],"teamName":null},{"rank":10,"team_id":20,"score":{"total_time":0,"num_solved":0},"problems":[{"solved":false,"num_judged":0,"problem_id":"Box","num_pending":0},{"solved":false,"num_judged":0,"problem_id":"Colour","num_pending":0},{"solved":false,"num_judged":0,"problem_id":"Game","num_pending":0},{"solved":false,"num_judged":0,"problem_id":"Hello","num_pending":0},{"solved":false,"num_judged":0,"problem_id":"Magic","num_pending":0},{"solved":false,"num_judged":0,"problem_id":"Matrix","num_pending":0},{"solved":false,"num_judged":0,"problem_id":"Rooms","num_pending":0},{"solved":false,"num_judged":0,"problem_id":"SumIt","num_pending":0},{"solved":false,"num_judged":0,"problem_id":"Tax","num_pending":0}],"teamName":null},{"rank":10,"team_id":19,"score":{"total_time":0,"num_solved":0},"problems":[{"solved":false,"num_judged":0,"problem_id":"Box","num_pending":0},{"solved":false,"num_judged":0,"problem_id":"Colour","num_pending":0},{"solved":false,"num_judged":0,"problem_id":"Game","num_pending":0},{"solved":false,"num_judged":0,"problem_id":"Hello","num_pending":0},{"solved":false,"num_judged":0,"problem_id":"Magic","num_pending":0},{"solved":false,"num_judged":0,"problem_id":"Matrix","num_pending":0},{"solved":false,"num_judged":0,"problem_id":"Rooms","num_pending":0},{"solved":false,"num_judged":0,"problem_id":"SumIt","num_pending":0},{"solved":false,"num_judged":0,"problem_id":"Tax","num_pending":0}],"teamName":null},{"rank":10,"team_id":7,"score":{"total_time":0,"num_solved":0},"problems":[{"solved":false,"num_judged":0,"problem_id":"Box","num_pending":0},{"solved":false,"num_judged":0,"problem_id":"Colour","num_pending":0},{"solved":false,"num_judged":0,"problem_id":"Game","num_pending":0},{"solved":false,"num_judged":0,"problem_id":"Hello","num_pending":0},{"solved":false,"num_judged":0,"problem_id":"Magic","num_pending":0},{"solved":false,"num_judged":0,"problem_id":"Matrix","num_pending":0},{"solved":false,"num_judged":0,"problem_id":"Rooms","num_pending":0},{"solved":false,"num_judged":0,"problem_id":"SumIt","num_pending":0},{"solved":false,"num_judged":0,"problem_id":"Tax","num_pending":0}],"teamName":null},{"rank":10,"team_id":16,"score":{"total_time":0,"num_solved":0},"problems":[{"solved":false,"num_judged":0,"problem_id":"Box","num_pending":0},{"solved":false,"num_judged":0,"problem_id":"Colour","num_pending":0},{"solved":false,"num_judged":0,"problem_id":"Game","num_pending":0},{"solved":false,"num_judged":0,"problem_id":"Hello","num_pending":0},{"solved":false,"num_judged":0,"problem_id":"Magic","num_pending":0},{"solved":false,"num_judged":0,"problem_id":"Matrix","num_pending":0},{"solved":false,"num_judged":0,"problem_id":"Rooms","num_pending":0},{"solved":false,"num_judged":0,"problem_id":"SumIt","num_pending":0},{"solved":false,"num_judged":0,"problem_id":"Tax","num_pending":0}],"teamName":null},{"rank":10,"team_id":17,"score":{"total_time":0,"num_solved":0},"problems":[{"solved":false,"num_judged":0,"problem_id":"Box","num_pending":0},{"solved":false,"num_judged":0,"problem_id":"Colour","num_pending":0},{"solved":false,"num_judged":0,"problem_id":"Game","num_pending":0},{"solved":false,"num_judged":0,"problem_id":"Hello","num_pending":0},{"solved":false,"num_judged":0,"problem_id":"Magic","num_pending":0},{"solved":false,"num_judged":0,"problem_id":"Matrix","num_pending":0},{"solved":false,"num_judged":0,"problem_id":"Rooms","num_pending":0},{"solved":false,"num_judged":0,"problem_id":"SumIt","num_pending":0},{"solved":false,"num_judged":0,"problem_id":"Tax","num_pending":0}],"teamName":null}]}
